sim/build/SPIHardbits__pack_size_128__hard_bits_4__pickled.v
//-------------------------------------------------------------------------
// SPIHardbits__pack_size_128__hard_bits_4.v
//-------------------------------------------------------------------------
// This file is generated by PyMTL SystemVerilog translation pass.

// PyMTL VerilogPlaceholder SPIHardbits Definition
// At /home/km633/Research/SPI_pymtl/sim/SPI_pymtl2/MinionModules/SPIHardbits/SPIHardbits.py

//***********************************************************
// Pickled source file of placeholder SPIHardbits__pack_size_128__hard_bits_4
//***********************************************************

//-----------------------------------------------------------
// Dependency of placeholder SPIHardbits
//-----------------------------------------------------------

`ifndef SPIHARDBITS
`define SPIHARDBITS

// The source code below are included because they are specified
// as the v_libs Verilog placeholder option of component SPIHardbits__pack_size_128__hard_bits_4.

// If you get a duplicated def error from files included below, please
// make sure they are included either through the v_libs option or the
// explicit `include statement in the Verilog source code -- if they
// appear in both then they will be included twice!


// End of all v_libs files for component SPIHardbits__pack_size_128__hard_bits_4

`line 1 "SPI_pymtl2/MinionModules/SPIHardbits/SPIHardbits.v" 0
//===========================================
// SPI Hardbits
//===========================================

`ifndef HARDBITS_V
`define HARDBITS_V


module SPI_pymtl2_MinionModules_SPIHardbits_SPIHardbits
#(
  parameter pack_size = 32,
  parameter hard_bits = 1
)(

  //control IO
  input  logic                    clk,
  input  logic                    reset,
  input  logic                    serve,
  output logic                    hard_msg,
  
  //IO with respect to master
  input  logic [pack_size-1 : 0]  from_master,
  output logic [pack_size-1 : 0]  to_master,

  
  //detected bits
  output logic [hard_bits-1 : 0]  detected_bits,
  
  //IO with respect to device
  input  logic [pack_size-1 : 0]  from_device,
  output logic [pack_size-1 : 0]  to_device
  
); 
  // message pass through
  assign to_device = from_master;
  assign to_master = from_device;
  
  // hard_msg signal
  assign hard_msg = from_master[pack_size - 1] ? 1'b1 : 1'b0;  
  
  // detected bits
  vc_EnResetReg  #(hard_bits, 0) bit_status
  (
    .clk        (clk),
    .reset      (reset),
    .q          (detected_bits),
    .d          (from_master[pack_size - 2 : pack_size - (hard_bits + 1)]),
    .en         (from_master[pack_size - 1] & serve)                //msb will be enable signal for hardcode
  );
        
endmodule 

//////////////////////////////////////////////////////////////////////////
// includes 
//////////////////////////////////////////////////////////////////////////
    
module vc_EnResetReg
#(
  parameter p_nbits       = 1,
  parameter p_reset_value = 0
)(
  input  logic               clk,   // Clock input
  input  logic               reset, // Sync reset input
  output logic [p_nbits-1:0] q,     // Data output
  input  logic [p_nbits-1:0] d,     // Data input
  input  logic               en     // Enable input
);

  always@( posedge clk )
    if ( reset || en )
      q <= reset ? p_reset_value : d;

endmodule

`endif /* HARDBITS_V */

`endif /* SPIHARDBITS */
//-----------------------------------------------------------
// Wrapper of placeholder SPIHardbits__pack_size_128__hard_bits_4
//-----------------------------------------------------------

`ifndef SPIHARDBITS__PACK_SIZE_128__HARD_BITS_4
`define SPIHARDBITS__PACK_SIZE_128__HARD_BITS_4

module SPIHardbits__pack_size_128__hard_bits_4
(
  input logic [1-1:0] clk ,
  output logic [4-1:0] detected_bits ,
  input logic [128-1:0] from_device ,
  input logic [128-1:0] from_master ,
  output logic [1-1:0] hard_msg ,
  input logic [1-1:0] reset ,
  input logic [1-1:0] serve ,
  output logic [128-1:0] to_device ,
  output logic [128-1:0] to_master 
);
  SPI_pymtl2_MinionModules_SPIHardbits_SPIHardbits
  #(
    .pack_size( 128 ),
    .hard_bits( 4 )
  ) v
  (
    .clk( clk ),
    .detected_bits( detected_bits ),
    .from_device( from_device ),
    .from_master( from_master ),
    .hard_msg( hard_msg ),
    .reset( reset ),
    .serve( serve ),
    .to_device( to_device ),
    .to_master( to_master )
  );
endmodule

`endif /* SPIHARDBITS__PACK_SIZE_128__HARD_BITS_4 */

sim/build/SPI_pymtl2.SPIStacks.FPUStack.test.FPUStack_test__test_stack_8bit_basic_0x0_top_fpu_stack_spi_stack_spi_hardbits.verilator1.vcd
$version Generated by VerilatedVcd $end
$date Thu Apr 22 15:42:14 2021
 $end
$timescale  10ps $end

 $scope module TOP $end
  $var wire  1 # clk [0:0] $end
  $var wire  4 $ detected_bits [3:0] $end
  $var wire 128 % from_device [127:0] $end
  $var wire 128 ) from_master [127:0] $end
  $var wire  1 - hard_msg [0:0] $end
  $var wire  1 . reset [0:0] $end
  $var wire  1 / serve [0:0] $end
  $var wire 128 0 to_device [127:0] $end
  $var wire 128 4 to_master [127:0] $end
  $scope module SPIHardbits__pack_size_128__hard_bits_4 $end
   $var wire  1 # clk [0:0] $end
   $var wire  4 $ detected_bits [3:0] $end
   $var wire 128 % from_device [127:0] $end
   $var wire 128 ) from_master [127:0] $end
   $var wire  1 - hard_msg [0:0] $end
   $var wire  1 . reset [0:0] $end
   $var wire  1 / serve [0:0] $end
   $var wire 128 0 to_device [127:0] $end
   $var wire 128 4 to_master [127:0] $end
   $scope module v $end
    $var wire  1 # clk $end
    $var wire  4 $ detected_bits [3:0] $end
    $var wire 128 % from_device [127:0] $end
    $var wire 128 ) from_master [127:0] $end
    $var wire 32 ; hard_bits [31:0] $end
    $var wire  1 - hard_msg $end
    $var wire 32 : pack_size [31:0] $end
    $var wire  1 . reset $end
    $var wire  1 / serve $end
    $var wire 128 0 to_device [127:0] $end
    $var wire 128 4 to_master [127:0] $end
    $scope module bit_status $end
     $var wire  1 # clk $end
     $var wire  4 8 d [3:0] $end
     $var wire  1 9 en $end
     $var wire 32 ; p_nbits [31:0] $end
     $var wire 32 < p_reset_value [31:0] $end
     $var wire  4 $ q [3:0] $end
     $var wire  1 . reset $end
    $upscope $end
   $upscope $end
  $upscope $end
 $upscope $end
$enddefinitions $end


#50
0#
b0000 $
b00000000000000000000000000000000000000000000000000000000000000000000000000000000000000000000000000000000000000000000000000000000 %
b00000000000000000000000000000000000000000000000000000000000000000000000000000000000000000000000000000000000000000000000000000000 )
0-
1.
0/
b00000000000000000000000000000000000000000000000000000000000000000000000000000000000000000000000000000000000000000000000000000000 0
b00000000000000000000000000000000000000000000000000000000000000000000000000000000000000000000000000000000000000000000000000000000 4
b0000 8
09
b00000000000000000000000010000000 :
b00000000000000000000000000000100 ;
b00000000000000000000000000000000 <
#100
1#
#150
0#
#200
1#
#250
0#
#300
1#
#350
0#
0.
#400
1#
#450
0#
#500
1#
#550
0#
#600
1#
#650
0#
#700
1#
#750
0#
#800
1#
#850
0#
#900
1#
#950
0#
#1000
1#
#1050
0#
#1100
1#
#1150
0#
#1200
1#
#1250
0#
#1300
1#
#1350
0#
#1400
1#
#1450
0#
#1500
1#
#1550
0#
#1600
1#
#1650
0#
#1700
1#
#1750
0#
#1800
1#
#1850
0#
#1900
1#
#1950
0#
#2000
1#
#2050
0#
#2100
1#
#2150
0#
#2200
1#
#2250
0#
#2300
1#
#2350
0#
#2400
1#
#2450
0#
#2500
1#
#2550
0#
#2600
1#
#2650
0#
#2700
1#
#2750
0#
#2800
1#
#2850
0#
#2900
1#
#2950
0#
#3000
1#
#3050
0#
#3100
1#
#3150
0#
#3200
1#
#3250
0#
#3300
1#
#3350
0#
#3400
1#
#3450
0#
#3500
1#
#3550
0#
#3600
1#
#3650
0#
#3700
1#
#3750
0#
#3800
1#
#3850
0#
#3900
1#
#3950
0#
#4000
1#
#4050
0#
#4100
1#
#4150
0#
#4200
1#
#4250
0#
#4300
1#
#4350
0#
#4400
1#
#4450
0#
#4500
1#
#4550
0#
#4600
1#
#4650
0#
#4700
1#
#4750
0#
#4800
1#
#4850
0#
#4900
1#
#4950
0#
#5000
1#
#5050
0#
#5100
1#
#5150
0#
#5200
1#
#5250
0#
#5300
1#
#5350
0#
#5400
1#
#5450
0#
#5500
1#
#5550
0#
#5600
1#
#5650
0#
#5700
1#
#5750
0#
#5800
1#
#5850
0#
#5900
1#
#5950
0#
#6000
1#
#6050
0#
#6100
1#
#6150
0#
#6200
1#
#6250
0#
#6300
1#
#6350
0#
#6400
1#
#6450
0#
#6500
1#
#6550
0#
#6600
1#
#6650
0#
#6700
1#
#6750
0#
#6800
1#
#6850
0#
#6900
1#
#6950
0#
#7000
1#
#7050
0#
#7100
1#
#7150
0#
#7200
1#
#7250
0#
#7300
1#
#7350
0#
#7400
1#
#7450
0#
#7500
1#
#7550
0#
#7600
1#
#7650
0#
#7700
1#
#7750
0#
#7800
1#
#7850
0#
#7900
1#
#7950
0#
#8000
1#
#8050
0#
#8100
1#
#8150
0#
#8200
1#
#8250
0#
#8300
1#
#8350
0#
#8400
1#
#8450
0#
#8500
1#
#8550
0#
#8600
1#
#8650
0#
#8700
1#
#8750
0#
#8800
1#
#8850
0#
#8900
1#
#8950
0#
#9000
1#
#9050
0#
#9100
1#
#9150
0#
#9200
1#
#9250
0#
#9300
1#
#9350
0#
#9400
1#
#9450
0#
#9500
1#
#9550
0#
#9600
1#
#9650
0#
#9700
1#
#9750
0#
#9800
1#
#9850
0#
#9900
1#
#9950
0#
#10000
1#
#10050
0#
#10100
1#
#10150
0#
#10200
1#
#10250
0#
#10300
1#
#10350
0#
#10400
1#
#10450
0#
#10500
1#
#10550
0#
#10600
1#
#10650
0#
#10700
1#
#10750
0#
#10800
1#
#10850
0#
#10900
1#
#10950
0#
#11000
1#
#11050
0#
#11100
1#
#11150
0#
#11200
1#
#11250
0#
#11300
1#
#11350
0#
#11400
1#
#11450
0#
#11500
1#
#11550
0#
#11600
1#
#11650
0#
#11700
1#
#11750
0#
#11800
1#
#11850
0#
#11900
1#
#11950
0#
#12000
1#
#12050
0#
#12100
1#
#12150
0#
#12200
1#
#12250
0#
#12300
1#
#12350
0#
#12400
1#
#12450
0#
#12500
1#
#12550
0#
#12600
1#
#12650
0#
#12700
1#
#12750
0#
#12800
1#
#12850
0#
#12900
1#
#12950
0#
#13000
1#
#13050
0#
#13100
1#
#13150
0#
#13200
1#
#13250
0#
#13300
1#
#13350
0#
#13400
1#
#13450
0#
#13500
1#
#13550
0#
#13600
1#
#13650
0#
#13700
1#
#13750
0#
#13800
1#
#13850
0#
#13900
1#
#13950
0#
#14000
1#
#14050
0#
#14100
1#
#14150
0#
#14200
1#
#14250
0#
#14300
1#
#14350
0#
#14400
1#
#14450
0#
#14500
1#
#14550
0#
#14600
1#
#14650
0#
#14700
1#
#14750
0#
#14800
1#
#14850
0#
#14900
1#
#14950
0#
#15000
1#
#15050
0#
#15100
1#
#15150
0#
#15200
1#
#15250
0#
#15300
1#
#15350
0#
#15400
1#
#15450
0#
#15500
1#
#15550
0#
#15600
1#
#15650
0#
#15700
1#
#15750
0#
#15800
1#
#15850
0#
#15900
1#
#15950
0#
#16000
1#
#16050
0#
#16100
1#
#16150
0#
#16200
1#
#16250
0#
#16300
1#
#16350
0#
#16400
1#
#16450
0#
#16500
1#
#16550
0#
#16600
1#
#16650
0#
#16700
1#
#16750
0#
#16800
1#
#16850
0#
#16900
1#
#16950
0#
#17000
1#
#17050
0#
#17100
1#
#17150
0#
#17200
1#
#17250
0#
#17300
1#
#17350
0#
#17400
1#
#17450
0#
#17500
1#
#17550
0#
#17600
1#
#17650
0#
#17700
1#
#17750
0#
#17800
1#
#17850
0#
#17900
1#
#17950
0#
#18000
1#
#18050
0#
#18100
1#
#18150
0#
#18200
1#
#18250
0#
#18300
1#
#18350
0#
#18400
1#
#18450
0#
#18500
1#
#18550
0#
#18600
1#
#18650
0#
#18700
1#
#18750
0#
#18800
1#
#18850
0#
#18900
1#
#18950
0#
#19000
1#
#19050
0#
#19100
1#
#19150
0#
#19200
1#
#19250
0#
#19300
1#
#19350
0#
#19400
1#
#19450
0#
#19500
1#
#19550
0#
#19600
1#
#19650
0#
#19700
1#
#19750
0#
#19800
1#
#19850
0#
#19900
1#
#19950
0#
#20000
1#
#20050
0#
#20100
1#
#20150
0#
#20200
1#
#20250
0#
#20300
1#
#20350
0#
#20400
1#
#20450
0#
#20500
1#
#20550
0#
#20600
1#
#20650
0#
#20700
1#
#20750
0#
#20800
1#
#20850
0#
#20900
1#
#20950
0#
#21000
1#
#21050
0#
#21100
1#
#21150
0#
#21200
1#
#21250
0#
#21300
1#
#21350
0#
#21400
1#
#21450
0#
#21500
1#
#21550
0#
#21600
1#
#21650
0#
#21700
1#
#21750
0#
#21800
1#
#21850
0#
#21900
1#
#21950
0#
#22000
1#
#22050
0#
#22100
1#
#22150
0#
#22200
1#
#22250
0#
#22300
1#
#22350
0#
#22400
1#
#22450
0#
#22500
1#
#22550
0#
#22600
1#
#22650
0#
#22700
1#
#22750
0#
#22800
1#
#22850
0#
#22900
1#
#22950
0#
#23000
1#
#23050
0#
#23100
1#
#23150
0#
#23200
1#
#23250
0#
#23300
1#
#23350
0#
#23400
1#
#23450
0#
#23500
1#
#23550
0#
#23600
1#
#23650
0#
#23700
1#
#23750
0#
#23800
1#
#23850
0#
#23900
1#
#23950
0#
#24000
1#
#24050
0#
#24100
1#
#24150
0#
#24200
1#
#24250
0#
#24300
1#
#24350
0#
#24400
1#
#24450
0#
#24500
1#
#24550
0#
#24600
1#
#24650
0#
#24700
1#
#24750
0#
#24800
1#
#24850
0#
#24900
1#
#24950
0#
#25000
1#
#25050
0#
#25100
1#
#25150
0#
#25200
1#
#25250
0#
#25300
1#
#25350
0#
#25400
1#
#25450
0#
#25500
1#
#25550
0#
#25600
1#
#25650
0#
#25700
1#
#25750
0#
#25800
1#
#25850
0#
#25900
1#
#25950
0#
#26000
1#
#26050
0#
#26100
1#
#26150
0#
#26200
1#
#26250
0#
#26300
1#
#26350
0#
#26400
1#
#26450
0#
#26500
1#
#26550
0#
#26600
1#
#26650
0#
#26700
1#
#26750
0#
#26800
1#
#26850
0#
#26900
1#
#26950
0#
#27000
1#
#27050
0#
#27100
1#
#27150
0#
#27200
1#
#27250
0#
#27300
1#
#27350
0#
#27400
1#
#27450
0#
#27500
1#
#27550
0#
#27600
1#
#27650
0#
#27700
1#
#27750
0#
#27800
1#
#27850
0#
#27900
1#
#27950
0#
#28000
1#
#28050
0#
#28100
1#
#28150
0#
#28200
1#
#28250
0#
#28300
1#
#28350
0#
#28400
1#
#28450
0#
#28500
1#
#28550
0#
#28600
1#
#28650
0#
#28700
1#
#28750
0#
#28800
1#
#28850
0#
#28900
1#
#28950
0#
#29000
1#
#29050
0#
#29100
1#
#29150
0#
#29200
1#
#29250
0#
#29300
1#
#29350
0#
#29400
1#
#29450
0#
#29500
1#
#29550
0#
#29600
1#
#29650
0#
#29700
1#
#29750
0#
#29800
1#
#29850
0#
#29900
1#
#29950
0#
#30000
1#
#30050
0#
#30100
1#
#30150
0#
#30200
1#
#30250
0#
#30300
1#
#30350
0#
#30400
1#
#30450
0#
#30500
1#
#30550
0#
#30600
1#
#30650
0#
#30700
1#
#30750
0#
#30800
1#
#30850
0#
#30900
1#
#30950
0#
#31000
1#
#31050
0#
#31100
1#
#31150
0#
#31200
1#
#31250
0#
#31300
1#
#31350
0#
#31400
1#
#31450
0#
#31500
1#
#31550
0#
#31600
1#
#31650
0#
#31700
1#
#31750
0#
#31800
1#
#31850
0#
#31900
1#
#31950
0#
#32000
1#
#32050
0#
#32100
1#
#32150
0#
#32200
1#
#32250
0#
#32300
1#
#32350
0#
#32400
1#
#32450
0#
#32500
1#
#32550
0#
#32600
1#
#32650
0#
#32700
1#
#32750
0#
#32800
1#
#32850
0#
#32900
1#
#32950
0#
#33000
1#
#33050
0#
#33100
1#
#33150
0#
#33200
1#
#33250
0#
#33300
1#
#33350
0#
#33400
1#
#33450
0#
#33500
1#
#33550
0#
#33600
1#
#33650
0#
#33700
1#
#33750
0#
#33800
1#
#33850
0#
#33900
1#
#33950
0#
#34000
1#
#34050
0#
#34100
1#
#34150
0#
#34200
1#
#34250
0#
#34300
1#
#34350
0#
#34400
1#
#34450
0#
#34500
1#
#34550
0#
#34600
1#
#34650
0#
#34700
1#
#34750
0#
#34800
1#
#34850
0#
#34900
1#
#34950
0#
#35000
1#
#35050
0#
#35100
1#
#35150
0#
#35200
1#
#35250
0#
#35300
1#
#35350
0#
#35400
1#
#35450
0#
#35500
1#
#35550
0#
#35600
1#
#35650
0#
#35700
1#
#35750
0#
#35800
1#
#35850
0#
#35900
1#
#35950
0#
#36000
1#
#36050
0#
#36100
1#
#36150
0#
#36200
1#
#36250
0#
#36300
1#
#36350
0#
#36400
1#
#36450
0#
#36500
1#
#36550
0#
#36600
1#
#36650
0#
#36700
1#
#36750
0#
#36800
1#
#36850
0#
#36900
1#
#36950
0#
#37000
1#
#37050
0#
#37100
1#
#37150
0#
#37200
1#
#37250
0#
#37300
1#
#37350
0#
#37400
1#
#37450
0#
#37500
1#
#37550
0#
#37600
1#
#37650
0#
#37700
1#
#37750
0#
#37800
1#
#37850
0#
#37900
1#
#37950
0#
#38000
1#
#38050
0#
#38100
1#
#38150
0#
#38200
1#
#38250
0#
#38300
1#
#38350
0#
#38400
1#
#38450
0#
#38500
1#
#38550
0#
#38600
1#
#38650
0#
#38700
1#
#38750
0#
#38800
1#
#38850
0#
#38900
1#
#38950
0#
#39000
1#
#39050
0#
#39100
1#
#39150
0#
#39200
1#
#39250
0#
#39300
1#
#39350
0#
#39400
1#
#39450
0#
#39500
1#
#39550
0#
#39600
1#
#39650
0#
#39700
1#
#39750
0#
#39800
1#
#39850
0#
#39900
1#
#39950
0#
#40000
1#
#40050
0#
#40100
1#
#40150
0#
#40200
1#
#40250
0#
#40300
1#
#40350
0#
#40400
1#
#40450
0#
#40500
1#
#40550
0#
#40600
1#
#40650
0#
#40700
1#
#40750
0#
#40800
1#
#40850
0#
#40900
1#
#40950
0#
#41000
1#
#41050
0#
#41100
1#
#41150
0#
#41200
1#
#41250
0#
#41300
1#
#41350
0#
#41400
1#
#41450
0#
#41500
1#
#41550
0#
#41600
1#
#41650
0#
#41700
1#
#41750
0#
#41800
1#
#41850
0#
#41900
1#
#41950
0#
#42000
1#
#42050
0#
#42100
1#
#42150
0#
#42200
1#
#42250
0#
#42300
1#
#42350
0#
#42400
1#
#42450
0#
#42500
1#
#42550
0#
#42600
1#
#42650
0#
#42700
1#
#42750
0#
#42800
1#
#42850
0#
#42900
1#
#42950
0#
#43000
1#
#43050
0#
#43100
1#
#43150
0#
#43200
1#
#43250
0#
#43300
1#
#43350
0#
#43400
1#
#43450
0#
#43500
1#
#43550
0#
#43600
1#
#43650
0#
#43700
1#
#43750
0#
#43800
1#
#43850
0#
#43900
1#
#43950
0#
#44000
1#
#44050
0#
#44100
1#
#44150
0#
#44200
1#
#44250
0#
#44300
1#
#44350
0#
#44400
1#
#44450
0#
#44500
1#
#44550
0#
#44600
1#
#44650
0#
#44700
1#
#44750
0#
#44800
1#
#44850
0#
#44900
1#
#44950
0#
#45000
1#
#45050
0#
#45100
1#
#45150
0#
#45200
1#
#45250
0#
#45300
1#
#45350
0#
#45400
1#
#45450
0#
#45500
1#
#45550
0#
#45600
1#
#45650
0#
#45700
1#
#45750
0#
#45800
1#
#45850
0#
#45900
1#
#45950
0#
#46000
1#
#46050
0#
#46100
1#
#46150
0#
#46200
1#
#46250
0#
#46300
1#
#46350
0#
#46400
1#
#46450
0#
#46500
1#
#46550
0#
#46600
1#
#46650
0#
#46700
1#
#46750
0#
#46800
1#
#46850
0#
#46900
1#
#46950
0#
#47000
1#
#47050
0#
#47100
1#
#47150
0#
#47200
1#
#47250
0#
#47300
1#
#47350
0#
#47400
1#
#47450
0#
#47500
1#
#47550
0#
#47600
1#
#47650
0#
#47700
1#
#47750
0#
#47800
1#
#47850
0#
#47900
1#
#47950
0#
#48000
1#
#48050
0#
#48100
1#
#48150
0#
#48200
1#
#48250
0#
#48300
1#
#48350
0#
#48400
1#
#48450
0#
#48500
1#
#48550
0#
#48600
1#
#48650
0#
#48700
1#
#48750
0#
#48800
1#
#48850
0#
#48900
1#
#48950
0#
#49000
1#
#49050
0#
#49100
1#
#49150
0#
#49200
1#
#49250
0#
#49300
1#
#49350
0#
#49400
1#
#49450
0#
#49500
1#
#49550
0#
#49600
1#
#49650
0#
#49700
1#
#49750
0#
#49800
1#
#49850
0#
#49900
1#
#49950
0#
#50000
1#
#50050
0#
#50100
1#
#50150
0#
#50200
1#
#50250
0#
#50300
1#
#50350
0#
#50400
1#
#50450
0#
#50500
1#
#50550
0#
#50600
1#
#50650
0#
#50700
1#
#50750
0#
#50800
1#
#50850
0#
#50900
1#
#50950
0#
#51000
1#
#51050
0#
#51100
1#
#51150
0#
#51200
1#
#51250
0#
#51300
1#
#51350
0#
#51400
1#
#51450
0#
#51500
1#
#51550
0#
#51600
1#
#51650
0#
#51700
1#
#51750
0#
#51800
1#
#51850
0#
#51900
1#
#51950
0#
#52000
1#
#52050
0#
#52100
1#
#52150
0#
#52200
1#
#52250
0#
#52300
1#
#52350
0#
#52400
1#
#52450
0#
#52500
1#
#52550
0#
#52600
1#
#52650
0#
b00000000000000000000000000000000000000000000000000000000000000000000000000000000000000000000000000000000000000000000000000000001 )
b00000000000000000000000000000000000000000000000000000000000000000000000000000000000000000000000000000000000000000000000000000001 0
#52700
1#
#52750
0#
#52800
1#
#52850
0#
#52900
1#
#52950
0#
#53000
1#
#53050
0#
#53100
1#
#53150
0#
#53200
1#
#53250
0#
#53300
1#
#53350
0#
#53400
1#
#53450
0#
b00000000000000000000000000000000000000000000000000000000000000000000000000000000000000000000000000000000000000000000000000000011 )
b00000000000000000000000000000000000000000000000000000000000000000000000000000000000000000000000000000000000000000000000000000011 0
#53500
1#
#53550
0#
#53600
1#
#53650
0#
#53700
1#
#53750
0#
#53800
1#
#53850
0#
#53900
1#
#53950
0#
#54000
1#
#54050
0#
#54100
1#
#54150
0#
#54200
1#
#54250
0#
b00000000000000000000000000000000000000000000000000000000000000000000000000000000000000000000000000000000000000000000000000000110 )
b00000000000000000000000000000000000000000000000000000000000000000000000000000000000000000000000000000000000000000000000000000110 0
#54300
1#
#54350
0#
#54400
1#
#54450
0#
#54500
1#
#54550
0#
#54600
1#
#54650
0#
#54700
1#
#54750
0#
#54800
1#
#54850
0#
#54900
1#
#54950
0#
#55000
1#
#55050
0#
b00000000000000000000000000000000000000000000000000000000000000000000000000000000000000000000000000000000000000000000000000001100 )
b00000000000000000000000000000000000000000000000000000000000000000000000000000000000000000000000000000000000000000000000000001100 0
#55100
1#
#55150
0#
#55200
1#
#55250
0#
#55300
1#
#55350
0#
#55400
1#
#55450
0#
#55500
1#
#55550
0#
#55600
1#
#55650
0#
#55700
1#
#55750
0#
#55800
1#
#55850
0#
b00000000000000000000000000000000000000000000000000000000000000000000000000000000000000000000000000000000000000000000000000011000 )
b00000000000000000000000000000000000000000000000000000000000000000000000000000000000000000000000000000000000000000000000000011000 0
#55900
1#
#55950
0#
#56000
1#
#56050
0#
#56100
1#
#56150
0#
#56200
1#
#56250
0#
#56300
1#
#56350
0#
#56400
1#
#56450
0#
#56500
1#
#56550
0#
#56600
1#
#56650
0#
b00000000000000000000000000000000000000000000000000000000000000000000000000000000000000000000000000000000000000000000000000110000 )
b00000000000000000000000000000000000000000000000000000000000000000000000000000000000000000000000000000000000000000000000000110000 0
#56700
1#
#56750
0#
#56800
1#
#56850
0#
#56900
1#
#56950
0#
#57000
1#
#57050
0#
#57100
1#
#57150
0#
#57200
1#
#57250
0#
#57300
1#
#57350
0#
#57400
1#
#57450
0#
b00000000000000000000000000000000000000000000000000000000000000000000000000000000000000000000000000000000000000000000000001100000 )
b00000000000000000000000000000000000000000000000000000000000000000000000000000000000000000000000000000000000000000000000001100000 0
#57500
1#
#57550
0#
#57600
1#
#57650
0#
#57700
1#
#57750
0#
#57800
1#
#57850
0#
#57900
1#
#57950
0#
#58000
1#
#58050
0#
#58100
1#
#58150
0#
#58200
1#
#58250
0#
b00000000000000000000000000000000000000000000000000000000000000000000000000000000000000000000000000000000000000000000000011000000 )
b00000000000000000000000000000000000000000000000000000000000000000000000000000000000000000000000000000000000000000000000011000000 0
#58300
1#
#58350
0#
#58400
1#
#58450
0#
#58500
1#
#58550
0#
#58600
1#
#58650
0#
#58700
1#
#58750
0#
#58800
1#
#58850
0#
#58900
1#
#58950
0#
#59000
1#
#59050
0#
b00000000000000000000000000000000000000000000000000000000000000000000000000000000000000000000000000000000000000000000000110000000 )
b00000000000000000000000000000000000000000000000000000000000000000000000000000000000000000000000000000000000000000000000110000000 0
#59100
1#
#59150
0#
#59200
1#
#59250
0#
#59300
1#
#59350
0#
#59400
1#
#59450
0#
#59500
1#
#59550
0#
#59600
1#
#59650
0#
#59700
1#
#59750
0#
#59800
1#
#59850
0#
b00000000000000000000000000000000000000000000000000000000000000000000000000000000000000000000000000000000000000000000001100000001 )
b00000000000000000000000000000000000000000000000000000000000000000000000000000000000000000000000000000000000000000000001100000001 0
#59900
1#
#59950
0#
#60000
1#
#60050
0#
#60100
1#
#60150
0#
#60200
1#
#60250
0#
#60300
1#
#60350
0#
#60400
1#
#60450
0#
#60500
1#
#60550
0#
#60600
1#
#60650
0#
b00000000000000000000000000000000000000000000000000000000000000000000000000000000000000000000000000000000000000000000011000000011 )
b00000000000000000000000000000000000000000000000000000000000000000000000000000000000000000000000000000000000000000000011000000011 0
#60700
1#
#60750
0#
#60800
1#
#60850
0#
#60900
1#
#60950
0#
#61000
1#
#61050
0#
#61100
1#
#61150
0#
#61200
1#
#61250
0#
#61300
1#
#61350
0#
#61400
1#
#61450
0#
b00000000000000000000000000000000000000000000000000000000000000000000000000000000000000000000000000000000000000000000110000000111 )
b00000000000000000000000000000000000000000000000000000000000000000000000000000000000000000000000000000000000000000000110000000111 0
#61500
1#
#61550
0#
#61600
1#
#61650
0#
#61700
1#
#61750
0#
#61800
1#
#61850
0#
#61900
1#
#61950
0#
#62000
1#
#62050
0#
#62100
1#
#62150
0#
#62200
1#
#62250
0#
b00000000000000000000000000000000000000000000000000000000000000000000000000000000000000000000000000000000000000000001100000001111 )
b00000000000000000000000000000000000000000000000000000000000000000000000000000000000000000000000000000000000000000001100000001111 0
#62300
1#
#62350
0#
#62400
1#
#62450
0#
#62500
1#
#62550
0#
#62600
1#
#62650
0#
#62700
1#
#62750
0#
#62800
1#
#62850
0#
#62900
1#
#62950
0#
#63000
1#
#63050
0#
b00000000000000000000000000000000000000000000000000000000000000000000000000000000000000000000000000000000000000000011000000011111 )
b00000000000000000000000000000000000000000000000000000000000000000000000000000000000000000000000000000000000000000011000000011111 0
#63100
1#
#63150
0#
#63200
1#
#63250
0#
#63300
1#
#63350
0#
#63400
1#
#63450
0#
#63500
1#
#63550
0#
#63600
1#
#63650
0#
#63700
1#
#63750
0#
#63800
1#
#63850
0#
b00000000000000000000000000000000000000000000000000000000000000000000000000000000000000000000000000000000000000000110000000111111 )
b00000000000000000000000000000000000000000000000000000000000000000000000000000000000000000000000000000000000000000110000000111111 0
#63900
1#
#63950
0#
#64000
1#
#64050
0#
#64100
1#
#64150
0#
#64200
1#
#64250
0#
#64300
1#
#64350
0#
#64400
1#
#64450
0#
#64500
1#
#64550
0#
#64600
1#
#64650
0#
b00000000000000000000000000000000000000000000000000000000000000000000000000000000000000000000000000000000000000001100000001111111 )
b00000000000000000000000000000000000000000000000000000000000000000000000000000000000000000000000000000000000000001100000001111111 0
#64700
1#
#64750
0#
#64800
1#
#64850
0#
#64900
1#
#64950
0#
#65000
1#
#65050
0#
#65100
1#
#65150
0#
#65200
1#
#65250
0#
#65300
1#
#65350
0#
#65400
1#
#65450
0#
b00000000000000000000000000000000000000000000000000000000000000000000000000000000000000000000000000000000000000011000000011111110 )
b00000000000000000000000000000000000000000000000000000000000000000000000000000000000000000000000000000000000000011000000011111110 0
#65500
1#
#65550
0#
#65600
1#
#65650
0#
#65700
1#
#65750
0#
#65800
1#
#65850
0#
#65900
1#
#65950
0#
#66000
1#
#66050
0#
#66100
1#
#66150
0#
#66200
1#
#66250
0#
b00000000000000000000000000000000000000000000000000000000000000000000000000000000000000000000000000000000000000110000000111111100 )
b00000000000000000000000000000000000000000000000000000000000000000000000000000000000000000000000000000000000000110000000111111100 0
#66300
1#
#66350
0#
#66400
1#
#66450
0#
#66500
1#
#66550
0#
#66600
1#
#66650
0#
#66700
1#
#66750
0#
#66800
1#
#66850
0#
#66900
1#
#66950
0#
#67000
1#
#67050
0#
b00000000000000000000000000000000000000000000000000000000000000000000000000000000000000000000000000000000000001100000001111111001 )
b00000000000000000000000000000000000000000000000000000000000000000000000000000000000000000000000000000000000001100000001111111001 0
#67100
1#
#67150
0#
#67200
1#
#67250
0#
#67300
1#
#67350
0#
#67400
1#
#67450
0#
#67500
1#
#67550
0#
#67600
1#
#67650
0#
#67700
1#
#67750
0#
#67800
1#
#67850
0#
b00000000000000000000000000000000000000000000000000000000000000000000000000000000000000000000000000000000000011000000011111110011 )
b00000000000000000000000000000000000000000000000000000000000000000000000000000000000000000000000000000000000011000000011111110011 0
#67900
1#
#67950
0#
#68000
1#
#68050
0#
#68100
1#
#68150
0#
#68200
1#
#68250
0#
#68300
1#
#68350
0#
#68400
1#
#68450
0#
#68500
1#
#68550
0#
#68600
1#
#68650
0#
b00000000000000000000000000000000000000000000000000000000000000000000000000000000000000000000000000000000000110000000111111100111 )
b00000000000000000000000000000000000000000000000000000000000000000000000000000000000000000000000000000000000110000000111111100111 0
#68700
1#
#68750
0#
#68800
1#
#68850
0#
#68900
1#
#68950
0#
#69000
1#
#69050
0#
#69100
1#
#69150
0#
#69200
1#
#69250
0#
#69300
1#
#69350
0#
#69400
1#
#69450
0#
b00000000000000000000000000000000000000000000000000000000000000000000000000000000000000000000000000000000001100000001111111001111 )
b00000000000000000000000000000000000000000000000000000000000000000000000000000000000000000000000000000000001100000001111111001111 0
#69500
1#
#69550
0#
#69600
1#
#69650
0#
#69700
1#
#69750
0#
#69800
1#
#69850
0#
#69900
1#
#69950
0#
#70000
1#
#70050
0#
#70100
1#
#70150
0#
#70200
1#
