sim/build/SPIMinion__pack_size_128__pickled.v
//-------------------------------------------------------------------------
// SPIMinion__pack_size_128.v
//-------------------------------------------------------------------------
// This file is generated by PyMTL SystemVerilog translation pass.

// PyMTL VerilogPlaceholder SPIMinion Definition
// At /home/km633/Research/SPI_pymtl/sim/SPI_pymtl2/MinionModules/SPIMinion/SPIMinion.py

//***********************************************************
// Pickled source file of placeholder SPIMinion__pack_size_128
//***********************************************************

//-----------------------------------------------------------
// Dependency of placeholder SPIMinion
//-----------------------------------------------------------

`ifndef SPIMINION
`define SPIMINION

// The source code below are included because they are specified
// as the v_libs Verilog placeholder option of component SPIMinion__pack_size_128.

// If you get a duplicated def error from files included below, please
// make sure they are included either through the v_libs option or the
// explicit `include statement in the Verilog source code -- if they
// appear in both then they will be included twice!


// End of all v_libs files for component SPIMinion__pack_size_128

`line 1 "SPI_pymtl2/MinionModules/SPIMinion/SPIMinion.v" 0
//===========================================
// SPI MINION
//===========================================

`ifndef MINION_V
`define MINION_V

module SPI_pymtl2_MinionModules_SPIMinion_SPIMinion
#(
  parameter pack_size = 32
)(
    
  input  logic                  clk,
  input  logic                  reset,
  output logic                  serve,
  output logic                  seize,  
  
  // IO with respect to device  
  input  logic [pack_size-1:0] from_device,   //Package to be sent back to master
  output logic [pack_size-1:0] to_device,     //message from master
   
  // input from Master
  input  logic                 sclk, 
  input  logic                 cs,              //active low
  input  logic                 mosi,

  // output to Master
  output logic                 miso
);
  //-------------------------------------------- 
  // Signal Sync
  //--------------------------------------------

  logic cs_synced;
  logic cs_posedge;
  logic cs_negedge;  
  
  SignalSync cs_sync_shift
  (
    .clk          (clk),
    .sig_in       (cs),
    .sig_synced   (cs_synced),
    .sig_posedge  (cs_posedge),
    .sig_negedge  (cs_negedge)
  );
    
  logic sclk_synced;
  logic sclk_posedge;
  logic sclk_negedge;  
  
  SignalSync sclk_sync_shift
  (
    .clk          (clk),
    .sig_in       (sclk),
    .sig_synced   (sclk_synced),
    .sig_posedge  (sclk_posedge),
    .sig_negedge  (sclk_negedge)
  );
  
  //-------------------------------------------- 
  // serve generation
  //--------------------------------------------
  
  always@(posedge clk) begin
    if (reset) begin
      serve <= 1'b0;
      seize <= 1'b0;
    end
  
    else begin
      serve <= cs_posedge ? 1'b1 : 1'b0;
      seize <= cs_negedge ? 1'b1 : 1'b0;      
    end  
  end  

  //-------------------------------------------- 
  // MOSI Shift Register (recieve MSB First)
  //--------------------------------------------

  logic [pack_size - 1:0] mosi_shift_reg_out;
  
  ShiftRegIn #(pack_size) mosi_shift_reg
  (
    .clk  (clk),
    .d    (mosi),
    .q    (mosi_shift_reg_out),
    .en   (sclk_posedge & !cs_synced)
  );

  assign to_device = mosi_shift_reg_out;

  //--------------------------------------------
  // MISO Shift Register
  //--------------------------------------------
  
  logic [pack_size - 1:0] miso_reg_out;
  
  ShiftRegOut #(pack_size) miso_shift_reg
  (
    .clk    (clk),
    .d      (from_device),
    .q      (miso_reg_out),
    .fill   (seize),
    .shift  (sclk_negedge)
  );
  
  assign miso = miso_reg_out[ pack_size - 1];
endmodule

//////////////////////////////////////////////////////////////////////////
// includes 
//////////////////////////////////////////////////////////////////////////

module vc_Reg
#(
  parameter p_nbits = 1
)(
  input  logic               clk, // Clock input
  output logic [p_nbits-1:0] q,   // Data output
  input  logic [p_nbits-1:0] d    // Data input
);

  always@( posedge clk )
    q <= d;

endmodule

module SignalSync
(
  input  logic                clk,
  input  logic                sig_in,
  
  output logic                sig_synced,
  output logic                sig_posedge,
  output logic                sig_negedge  
);
  
  logic [2:0] q;

  always@( posedge clk ) q <= {q[1:0], sig_in};
  
  assign sig_synced  = q[1];
  assign sig_posedge = (q[2:1] == 2'b01);
  assign sig_negedge = (q[2:1] == 2'b10);

endmodule

//------------------------------------------------------------------------
// Postive-edge shift register
//------------------------------------------------------------------------

//recieve MSB first
module ShiftRegIn                   
#(
  parameter p_nbits = 1
)(
  input  logic                 clk, // Clock input
  output logic [p_nbits - 1:0] q,   // Data output (whole user defined output)
  input  logic                 d,   // Data input  (one bit)
  input  logic                 en 
);

  always@( posedge clk )
    if ( en )
      q <= {q[p_nbits - 1:0], d};

endmodule

//------------------------------------------------------------------------
// Postive-edge shift register with instant fill
//------------------------------------------------------------------------

//send MSB first
module ShiftRegOut
#(
  parameter p_nbits = 1           
)(
  input  logic               clk, // Clock input
  output logic [p_nbits-1:0] q,   // Data output (bit, but MSB changes)
  input  logic [p_nbits-1:0] d,   // Data input  (whole user defined output)
  input  logic               fill,
  input  logic               shift 
);

  always@( posedge clk )
    if ( fill )
      q <= d;
    
    else if (!fill & shift) begin     
      q <= {q[p_nbits-1:0], 1'b0};
    end
    
endmodule
`endif /* MINION_V */

`endif /* SPIMINION */
//-----------------------------------------------------------
// Wrapper of placeholder SPIMinion__pack_size_128
//-----------------------------------------------------------

`ifndef SPIMINION__PACK_SIZE_128
`define SPIMINION__PACK_SIZE_128

module SPIMinion__pack_size_128
(
  input logic [1-1:0] clk ,
  input logic [1-1:0] cs ,
  input logic [128-1:0] from_device ,
  output logic [1-1:0] miso ,
  input logic [1-1:0] mosi ,
  input logic [1-1:0] reset ,
  input logic [1-1:0] sclk ,
  output logic [1-1:0] seize ,
  output logic [1-1:0] serve ,
  output logic [128-1:0] to_device 
);
  SPI_pymtl2_MinionModules_SPIMinion_SPIMinion
  #(
    .pack_size( 128 )
  ) v
  (
    .clk( clk ),
    .cs( cs ),
    .from_device( from_device ),
    .miso( miso ),
    .mosi( mosi ),
    .reset( reset ),
    .sclk( sclk ),
    .seize( seize ),
    .serve( serve ),
    .to_device( to_device )
  );
endmodule

`endif /* SPIMINION__PACK_SIZE_128 */

sim/build/SPI_pymtl2.SPIStacks.FPUStack.test.FPUStack_test__test_stack_8bit_basic_0x0_top_fpu_stack_spi_stack_spi_minion.verilator1.vcd
$version Generated by VerilatedVcd $end
$date Thu Apr 22 15:42:14 2021
 $end
$timescale  10ps $end

 $scope module TOP $end
  $var wire  1 4 clk [0:0] $end
  $var wire  1 5 cs [0:0] $end
  $var wire 128 6 from_device [127:0] $end
  $var wire  1 : miso [0:0] $end
  $var wire  1 ; mosi [0:0] $end
  $var wire  1 < reset [0:0] $end
  $var wire  1 = sclk [0:0] $end
  $var wire  1 > seize [0:0] $end
  $var wire  1 ? serve [0:0] $end
  $var wire 128 @ to_device [127:0] $end
  $scope module SPIMinion__pack_size_128 $end
   $var wire  1 4 clk [0:0] $end
   $var wire  1 5 cs [0:0] $end
   $var wire 128 6 from_device [127:0] $end
   $var wire  1 : miso [0:0] $end
   $var wire  1 ; mosi [0:0] $end
   $var wire  1 < reset [0:0] $end
   $var wire  1 = sclk [0:0] $end
   $var wire  1 > seize [0:0] $end
   $var wire  1 ? serve [0:0] $end
   $var wire 128 @ to_device [127:0] $end
   $scope module v $end
    $var wire  1 4 clk $end
    $var wire  1 5 cs $end
    $var wire  1 % cs_negedge $end
    $var wire  1 $ cs_posedge $end
    $var wire  1 # cs_synced $end
    $var wire 128 6 from_device [127:0] $end
    $var wire  1 : miso $end
    $var wire 128 - miso_reg_out [127:0] $end
    $var wire  1 ; mosi $end
    $var wire 128 ) mosi_shift_reg_out [127:0] $end
    $var wire 32 D pack_size [31:0] $end
    $var wire  1 < reset $end
    $var wire  1 = sclk $end
    $var wire  1 ( sclk_negedge $end
    $var wire  1 ' sclk_posedge $end
    $var wire  1 & sclk_synced $end
    $var wire  1 > seize $end
    $var wire  1 ? serve $end
    $var wire 128 @ to_device [127:0] $end
    $scope module cs_sync_shift $end
     $var wire  1 4 clk $end
     $var wire  3 1 q [2:0] $end
     $var wire  1 5 sig_in $end
     $var wire  1 % sig_negedge $end
     $var wire  1 $ sig_posedge $end
     $var wire  1 # sig_synced $end
    $upscope $end
    $scope module miso_shift_reg $end
     $var wire  1 4 clk $end
     $var wire 128 6 d [127:0] $end
     $var wire  1 > fill $end
     $var wire 32 D p_nbits [31:0] $end
     $var wire 128 - q [127:0] $end
     $var wire  1 ( shift $end
    $upscope $end
    $scope module mosi_shift_reg $end
     $var wire  1 4 clk $end
     $var wire  1 ; d $end
     $var wire  1 3 en $end
     $var wire 32 D p_nbits [31:0] $end
     $var wire 128 ) q [127:0] $end
    $upscope $end
    $scope module sclk_sync_shift $end
     $var wire  1 4 clk $end
     $var wire  3 2 q [2:0] $end
     $var wire  1 = sig_in $end
     $var wire  1 ( sig_negedge $end
     $var wire  1 ' sig_posedge $end
     $var wire  1 & sig_synced $end
    $upscope $end
   $upscope $end
  $upscope $end
 $upscope $end
$enddefinitions $end


#50
0#
0$
0%
0&
0'
0(
b00000000000000000000000000000000000000000000000000000000000000000000000000000000000000000000000000000000000000000000000000000000 )
b00000000000000000000000000000000000000000000000000000000000000000000000000000000000000000000000000000000000000000000000000000000 -
b000 1
b000 2
03
04
15
b00000000000000000000000000000000000000000000000000000000000000000000000000000000000000000000000000000000000000000000000000000000 6
0:
0;
1<
0=
0>
0?
b00000000000000000000000000000000000000000000000000000000000000000000000000000000000000000000000000000000000000000000000000000000 @
b00000000000000000000000010000000 D
#100
b001 1
14
#150
04
#200
1#
1$
b011 1
14
#250
04
#300
0$
b111 1
14
#350
04
0<
#400
14
#450
04
#500
14
#550
04
05
#600
b110 1
14
#650
04
#700
0#
1%
b100 1
14
#750
04
#800
0%
b000 1
14
1>
#850
04
#900
14
0>
#950
04
#1000
14
#1050
04
#1100
14
#1150
04
1=
#1200
b001 2
14
#1250
04
#1300
1&
1'
b011 2
13
14
#1350
04
#1400
0'
b111 2
03
14
#1450
04
#1500
14
#1550
04
0=
#1600
b110 2
14
#1650
04
#1700
0&
1(
b100 2
14
#1750
04
#1800
0(
b000 2
14
#1850
04
#1900
14
#1950
04
1=
#2000
b001 2
14
#2050
04
#2100
1&
1'
b011 2
13
14
#2150
04
#2200
0'
b111 2
03
14
#2250
04
#2300
14
#2350
04
0=
#2400
b110 2
14
#2450
04
#2500
0&
1(
b100 2
14
#2550
04
#2600
0(
b000 2
14
#2650
04
#2700
14
#2750
04
1=
#2800
b001 2
14
#2850
04
#2900
1&
1'
b011 2
13
14
#2950
04
#3000
0'
b111 2
03
14
#3050
04
#3100
14
#3150
04
0=
#3200
b110 2
14
#3250
04
#3300
0&
1(
b100 2
14
#3350
04
#3400
0(
b000 2
14
#3450
04
#3500
14
#3550
04
1=
#3600
b001 2
14
#3650
04
#3700
1&
1'
b011 2
13
14
#3750
04
#3800
0'
b111 2
03
14
#3850
04
#3900
14
#3950
04
0=
#4000
b110 2
14
#4050
04
#4100
0&
1(
b100 2
14
#4150
04
#4200
0(
b000 2
14
#4250
04
#4300
14
#4350
04
1=
#4400
b001 2
14
#4450
04
#4500
1&
1'
b011 2
13
14
#4550
04
#4600
0'
b111 2
03
14
#4650
04
#4700
14
#4750
04
0=
#4800
b110 2
14
#4850
04
#4900
0&
1(
b100 2
14
#4950
04
#5000
0(
b000 2
14
#5050
04
#5100
14
#5150
04
1=
#5200
b001 2
14
#5250
04
#5300
1&
1'
b011 2
13
14
#5350
04
#5400
0'
b111 2
03
14
#5450
04
#5500
14
#5550
04
0=
#5600
b110 2
14
#5650
04
#5700
0&
1(
b100 2
14
#5750
04
#5800
0(
b000 2
14
#5850
04
#5900
14
#5950
04
1=
#6000
b001 2
14
#6050
04
#6100
1&
1'
b011 2
13
14
#6150
04
#6200
0'
b111 2
03
14
#6250
04
#6300
14
#6350
04
0=
#6400
b110 2
14
#6450
04
#6500
0&
1(
b100 2
14
#6550
04
#6600
0(
b000 2
14
#6650
04
#6700
14
#6750
04
1=
#6800
b001 2
14
#6850
04
#6900
1&
1'
b011 2
13
14
#6950
04
#7000
0'
b111 2
03
14
#7050
04
#7100
14
#7150
04
0=
#7200
b110 2
14
#7250
04
#7300
0&
1(
b100 2
14
#7350
04
#7400
0(
b000 2
14
#7450
04
#7500
14
#7550
04
1=
#7600
b001 2
14
#7650
04
#7700
1&
1'
b011 2
13
14
#7750
04
#7800
0'
b111 2
03
14
#7850
04
#7900
14
#7950
04
0=
#8000
b110 2
14
#8050
04
#8100
0&
1(
b100 2
14
#8150
04
#8200
0(
b000 2
14
#8250
04
#8300
14
#8350
04
1=
#8400
b001 2
14
#8450
04
#8500
1&
1'
b011 2
13
14
#8550
04
#8600
0'
b111 2
03
14
#8650
04
#8700
14
#8750
04
0=
#8800
b110 2
14
#8850
04
#8900
0&
1(
b100 2
14
#8950
04
#9000
0(
b000 2
14
#9050
04
#9100
14
#9150
04
1=
#9200
b001 2
14
#9250
04
#9300
1&
1'
b011 2
13
14
#9350
04
#9400
0'
b111 2
03
14
#9450
04
#9500
14
#9550
04
0=
#9600
b110 2
14
#9650
04
#9700
0&
1(
b100 2
14
#9750
04
#9800
0(
b000 2
14
#9850
04
#9900
14
#9950
04
1=
#10000
b001 2
14
#10050
04
#10100
1&
1'
b011 2
13
14
#10150
04
#10200
0'
b111 2
03
14
#10250
04
#10300
14
#10350
04
0=
#10400
b110 2
14
#10450
04
#10500
0&
1(
b100 2
14
#10550
04
#10600
0(
b000 2
14
#10650
04
#10700
14
#10750
04
1=
#10800
b001 2
14
#10850
04
#10900
1&
1'
b011 2
13
14
#10950
04
#11000
0'
b111 2
03
14
#11050
04
#11100
14
#11150
04
0=
#11200
b110 2
14
#11250
04
#11300
0&
1(
b100 2
14
#11350
04
#11400
0(
b000 2
14
#11450
04
#11500
14
#11550
04
1=
#11600
b001 2
14
#11650
04
#11700
1&
1'
b011 2
13
14
#11750
04
#11800
0'
b111 2
03
14
#11850
04
#11900
14
#11950
04
0=
#12000
b110 2
14
#12050
04
#12100
0&
1(
b100 2
14
#12150
04
#12200
0(
b000 2
14
#12250
04
#12300
14
#12350
04
1=
#12400
b001 2
14
#12450
04
#12500
1&
1'
b011 2
13
14
#12550
04
#12600
0'
b111 2
03
14
#12650
04
#12700
14
#12750
04
0=
#12800
b110 2
14
#12850
04
#12900
0&
1(
b100 2
14
#12950
04
#13000
0(
b000 2
14
#13050
04
#13100
14
#13150
04
1=
#13200
b001 2
14
#13250
04
#13300
1&
1'
b011 2
13
14
#13350
04
#13400
0'
b111 2
03
14
#13450
04
#13500
14
#13550
04
0=
#13600
b110 2
14
#13650
04
#13700
0&
1(
b100 2
14
#13750
04
#13800
0(
b000 2
14
#13850
04
#13900
14
#13950
04
1=
#14000
b001 2
14
#14050
04
#14100
1&
1'
b011 2
13
14
#14150
04
#14200
0'
b111 2
03
14
#14250
04
#14300
14
#14350
04
0=
#14400
b110 2
14
#14450
04
#14500
0&
1(
b100 2
14
#14550
04
#14600
0(
b000 2
14
#14650
04
#14700
14
#14750
04
1=
#14800
b001 2
14
#14850
04
#14900
1&
1'
b011 2
13
14
#14950
04
#15000
0'
b111 2
03
14
#15050
04
#15100
14
#15150
04
0=
#15200
b110 2
14
#15250
04
#15300
0&
1(
b100 2
14
#15350
04
#15400
0(
b000 2
14
#15450
04
#15500
14
#15550
04
1=
#15600
b001 2
14
#15650
04
#15700
1&
1'
b011 2
13
14
#15750
04
#15800
0'
b111 2
03
14
#15850
04
#15900
14
#15950
04
0=
#16000
b110 2
14
#16050
04
#16100
0&
1(
b100 2
14
#16150
04
#16200
0(
b000 2
14
#16250
04
#16300
14
#16350
04
1=
#16400
b001 2
14
#16450
04
#16500
1&
1'
b011 2
13
14
#16550
04
#16600
0'
b111 2
03
14
#16650
04
#16700
14
#16750
04
0=
#16800
b110 2
14
#16850
04
#16900
0&
1(
b100 2
14
#16950
04
#17000
0(
b000 2
14
#17050
04
#17100
14
#17150
04
1=
#17200
b001 2
14
#17250
04
#17300
1&
1'
b011 2
13
14
#17350
04
#17400
0'
b111 2
03
14
#17450
04
#17500
14
#17550
04
0=
#17600
b110 2
14
#17650
04
#17700
0&
1(
b100 2
14
#17750
04
#17800
0(
b000 2
14
#17850
04
#17900
14
#17950
04
1=
#18000
b001 2
14
#18050
04
#18100
1&
1'
b011 2
13
14
#18150
04
#18200
0'
b111 2
03
14
#18250
04
#18300
14
#18350
04
0=
#18400
b110 2
14
#18450
04
#18500
0&
1(
b100 2
14
#18550
04
#18600
0(
b000 2
14
#18650
04
#18700
14
#18750
04
1=
#18800
b001 2
14
#18850
04
#18900
1&
1'
b011 2
13
14
#18950
04
#19000
0'
b111 2
03
14
#19050
04
#19100
14
#19150
04
0=
#19200
b110 2
14
#19250
04
#19300
0&
1(
b100 2
14
#19350
04
#19400
0(
b000 2
14
#19450
04
#19500
14
#19550
04
1=
#19600
b001 2
14
#19650
04
#19700
1&
1'
b011 2
13
14
#19750
04
#19800
0'
b111 2
03
14
#19850
04
#19900
14
#19950
04
0=
#20000
b110 2
14
#20050
04
#20100
0&
1(
b100 2
14
#20150
04
#20200
0(
b000 2
14
#20250
04
#20300
14
#20350
04
1=
#20400
b001 2
14
#20450
04
#20500
1&
1'
b011 2
13
14
#20550
04
#20600
0'
b111 2
03
14
#20650
04
#20700
14
#20750
04
0=
#20800
b110 2
14
#20850
04
#20900
0&
1(
b100 2
14
#20950
04
#21000
0(
b000 2
14
#21050
04
#21100
14
#21150
04
1=
#21200
b001 2
14
#21250
04
#21300
1&
1'
b011 2
13
14
#21350
04
#21400
0'
b111 2
03
14
#21450
04
#21500
14
#21550
04
0=
#21600
b110 2
14
#21650
04
#21700
0&
1(
b100 2
14
#21750
04
#21800
0(
b000 2
14
#21850
04
#21900
14
#21950
04
1=
#22000
b001 2
14
#22050
04
#22100
1&
1'
b011 2
13
14
#22150
04
#22200
0'
b111 2
03
14
#22250
04
#22300
14
#22350
04
0=
#22400
b110 2
14
#22450
04
#22500
0&
1(
b100 2
14
#22550
04
#22600
0(
b000 2
14
#22650
04
#22700
14
#22750
04
1=
#22800
b001 2
14
#22850
04
#22900
1&
1'
b011 2
13
14
#22950
04
#23000
0'
b111 2
03
14
#23050
04
#23100
14
#23150
04
0=
#23200
b110 2
14
#23250
04
#23300
0&
1(
b100 2
14
#23350
04
#23400
0(
b000 2
14
#23450
04
#23500
14
#23550
04
1=
#23600
b001 2
14
#23650
04
#23700
1&
1'
b011 2
13
14
#23750
04
#23800
0'
b111 2
03
14
#23850
04
#23900
14
#23950
04
0=
#24000
b110 2
14
#24050
04
#24100
0&
1(
b100 2
14
#24150
04
#24200
0(
b000 2
14
#24250
04
#24300
14
#24350
04
1=
#24400
b001 2
14
#24450
04
#24500
1&
1'
b011 2
13
14
#24550
04
#24600
0'
b111 2
03
14
#24650
04
#24700
14
#24750
04
0=
#24800
b110 2
14
#24850
04
#24900
0&
1(
b100 2
14
#24950
04
#25000
0(
b000 2
14
#25050
04
#25100
14
#25150
04
1=
#25200
b001 2
14
#25250
04
#25300
1&
1'
b011 2
13
14
#25350
04
#25400
0'
b111 2
03
14
#25450
04
#25500
14
#25550
04
0=
#25600
b110 2
14
#25650
04
#25700
0&
1(
b100 2
14
#25750
04
#25800
0(
b000 2
14
#25850
04
#25900
14
#25950
04
1=
#26000
b001 2
14
#26050
04
#26100
1&
1'
b011 2
13
14
#26150
04
#26200
0'
b111 2
03
14
#26250
04
#26300
14
#26350
04
0=
#26400
b110 2
14
#26450
04
#26500
0&
1(
b100 2
14
#26550
04
#26600
0(
b000 2
14
#26650
04
#26700
14
#26750
04
1=
#26800
b001 2
14
#26850
04
#26900
1&
1'
b011 2
13
14
#26950
04
#27000
0'
b111 2
03
14
#27050
04
#27100
14
#27150
04
0=
#27200
b110 2
14
#27250
04
#27300
0&
1(
b100 2
14
#27350
04
#27400
0(
b000 2
14
#27450
04
#27500
14
#27550
04
1=
#27600
b001 2
14
#27650
04
#27700
1&
1'
b011 2
13
14
#27750
04
#27800
0'
b111 2
03
14
#27850
04
#27900
14
#27950
04
0=
#28000
b110 2
14
#28050
04
#28100
0&
1(
b100 2
14
#28150
04
#28200
0(
b000 2
14
#28250
04
#28300
14
#28350
04
1=
#28400
b001 2
14
#28450
04
#28500
1&
1'
b011 2
13
14
#28550
04
#28600
0'
b111 2
03
14
#28650
04
#28700
14
#28750
04
0=
#28800
b110 2
14
#28850
04
#28900
0&
1(
b100 2
14
#28950
04
#29000
0(
b000 2
14
#29050
04
#29100
14
#29150
04
1=
#29200
b001 2
14
#29250
04
#29300
1&
1'
b011 2
13
14
#29350
04
#29400
0'
b111 2
03
14
#29450
04
#29500
14
#29550
04
0=
#29600
b110 2
14
#29650
04
#29700
0&
1(
b100 2
14
#29750
04
#29800
0(
b000 2
14
#29850
04
#29900
14
#29950
04
1=
#30000
b001 2
14
#30050
04
#30100
1&
1'
b011 2
13
14
#30150
04
#30200
0'
b111 2
03
14
#30250
04
#30300
14
#30350
04
0=
#30400
b110 2
14
#30450
04
#30500
0&
1(
b100 2
14
#30550
04
#30600
0(
b000 2
14
#30650
04
#30700
14
#30750
04
1=
#30800
b001 2
14
#30850
04
#30900
1&
1'
b011 2
13
14
#30950
04
#31000
0'
b111 2
03
14
#31050
04
#31100
14
#31150
04
0=
#31200
b110 2
14
#31250
04
#31300
0&
1(
b100 2
14
#31350
04
#31400
0(
b000 2
14
#31450
04
#31500
14
#31550
04
1=
#31600
b001 2
14
#31650
04
#31700
1&
1'
b011 2
13
14
#31750
04
#31800
0'
b111 2
03
14
#31850
04
#31900
14
#31950
04
0=
#32000
b110 2
14
#32050
04
#32100
0&
1(
b100 2
14
#32150
04
#32200
0(
b000 2
14
#32250
04
#32300
14
#32350
04
1=
#32400
b001 2
14
#32450
04
#32500
1&
1'
b011 2
13
14
#32550
04
#32600
0'
b111 2
03
14
#32650
04
#32700
14
#32750
04
0=
#32800
b110 2
14
#32850
04
#32900
0&
1(
b100 2
14
#32950
04
#33000
0(
b000 2
14
#33050
04
#33100
14
#33150
04
1=
#33200
b001 2
14
#33250
04
#33300
1&
1'
b011 2
13
14
#33350
04
#33400
0'
b111 2
03
14
#33450
04
#33500
14
#33550
04
0=
#33600
b110 2
14
#33650
04
#33700
0&
1(
b100 2
14
#33750
04
#33800
0(
b000 2
14
#33850
04
#33900
14
#33950
04
1=
#34000
b001 2
14
#34050
04
#34100
1&
1'
b011 2
13
14
#34150
04
#34200
0'
b111 2
03
14
#34250
04
#34300
14
#34350
04
0=
#34400
b110 2
14
#34450
04
#34500
0&
1(
b100 2
14
#34550
04
#34600
0(
b000 2
14
#34650
04
#34700
14
#34750
04
1=
#34800
b001 2
14
#34850
04
#34900
1&
1'
b011 2
13
14
#34950
04
#35000
0'
b111 2
03
14
#35050
04
#35100
14
#35150
04
0=
#35200
b110 2
14
#35250
04
#35300
0&
1(
b100 2
14
#35350
04
#35400
0(
b000 2
14
#35450
04
#35500
14
#35550
04
1=
#35600
b001 2
14
#35650
04
#35700
1&
1'
b011 2
13
14
#35750
04
#35800
0'
b111 2
03
14
#35850
04
#35900
14
#35950
04
0=
#36000
b110 2
14
#36050
04
#36100
0&
1(
b100 2
14
#36150
04
#36200
0(
b000 2
14
#36250
04
#36300
14
#36350
04
1=
#36400
b001 2
14
#36450
04
#36500
1&
1'
b011 2
13
14
#36550
04
#36600
0'
b111 2
03
14
#36650
04
#36700
14
#36750
04
0=
#36800
b110 2
14
#36850
04
#36900
0&
1(
b100 2
14
#36950
04
#37000
0(
b000 2
14
#37050
04
#37100
14
#37150
04
1=
#37200
b001 2
14
#37250
04
#37300
1&
1'
b011 2
13
14
#37350
04
#37400
0'
b111 2
03
14
#37450
04
#37500
14
#37550
04
0=
#37600
b110 2
14
#37650
04
#37700
0&
1(
b100 2
14
#37750
04
#37800
0(
b000 2
14
#37850
04
#37900
14
#37950
04
1=
#38000
b001 2
14
#38050
04
#38100
1&
1'
b011 2
13
14
#38150
04
#38200
0'
b111 2
03
14
#38250
04
#38300
14
#38350
04
0=
#38400
b110 2
14
#38450
04
#38500
0&
1(
b100 2
14
#38550
04
#38600
0(
b000 2
14
#38650
04
#38700
14
#38750
04
1=
#38800
b001 2
14
#38850
04
#38900
1&
1'
b011 2
13
14
#38950
04
#39000
0'
b111 2
03
14
#39050
04
#39100
14
#39150
04
0=
#39200
b110 2
14
#39250
04
#39300
0&
1(
b100 2
14
#39350
04
#39400
0(
b000 2
14
#39450
04
#39500
14
#39550
04
1=
#39600
b001 2
14
#39650
04
#39700
1&
1'
b011 2
13
14
#39750
04
#39800
0'
b111 2
03
14
#39850
04
#39900
14
#39950
04
0=
#40000
b110 2
14
#40050
04
#40100
0&
1(
b100 2
14
#40150
04
#40200
0(
b000 2
14
#40250
04
#40300
14
#40350
04
1=
#40400
b001 2
14
#40450
04
#40500
1&
1'
b011 2
13
14
#40550
04
#40600
0'
b111 2
03
14
#40650
04
#40700
14
#40750
04
0=
#40800
b110 2
14
#40850
04
#40900
0&
1(
b100 2
14
#40950
04
#41000
0(
b000 2
14
#41050
04
#41100
14
#41150
04
1=
#41200
b001 2
14
#41250
04
#41300
1&
1'
b011 2
13
14
#41350
04
#41400
0'
b111 2
03
14
#41450
04
#41500
14
#41550
04
0=
#41600
b110 2
14
#41650
04
#41700
0&
1(
b100 2
14
#41750
04
#41800
0(
b000 2
14
#41850
04
#41900
14
#41950
04
1=
#42000
b001 2
14
#42050
04
#42100
1&
1'
b011 2
13
14
#42150
04
#42200
0'
b111 2
03
14
#42250
04
#42300
14
#42350
04
0=
#42400
b110 2
14
#42450
04
#42500
0&
1(
b100 2
14
#42550
04
#42600
0(
b000 2
14
#42650
04
#42700
14
#42750
04
1=
#42800
b001 2
14
#42850
04
#42900
1&
1'
b011 2
13
14
#42950
04
#43000
0'
b111 2
03
14
#43050
04
#43100
14
#43150
04
0=
#43200
b110 2
14
#43250
04
#43300
0&
1(
b100 2
14
#43350
04
#43400
0(
b000 2
14
#43450
04
#43500
14
#43550
04
1=
#43600
b001 2
14
#43650
04
#43700
1&
1'
b011 2
13
14
#43750
04
#43800
0'
b111 2
03
14
#43850
04
#43900
14
#43950
04
0=
#44000
b110 2
14
#44050
04
#44100
0&
1(
b100 2
14
#44150
04
#44200
0(
b000 2
14
#44250
04
#44300
14
#44350
04
1=
#44400
b001 2
14
#44450
04
#44500
1&
1'
b011 2
13
14
#44550
04
#44600
0'
b111 2
03
14
#44650
04
#44700
14
#44750
04
0=
#44800
b110 2
14
#44850
04
#44900
0&
1(
b100 2
14
#44950
04
#45000
0(
b000 2
14
#45050
04
#45100
14
#45150
04
1=
#45200
b001 2
14
#45250
04
#45300
1&
1'
b011 2
13
14
#45350
04
#45400
0'
b111 2
03
14
#45450
04
#45500
14
#45550
04
0=
#45600
b110 2
14
#45650
04
#45700
0&
1(
b100 2
14
#45750
04
#45800
0(
b000 2
14
#45850
04
#45900
14
#45950
04
1=
#46000
b001 2
14
#46050
04
#46100
1&
1'
b011 2
13
14
#46150
04
#46200
0'
b111 2
03
14
#46250
04
#46300
14
#46350
04
0=
#46400
b110 2
14
#46450
04
#46500
0&
1(
b100 2
14
#46550
04
#46600
0(
b000 2
14
#46650
04
#46700
14
#46750
04
1=
#46800
b001 2
14
#46850
04
#46900
1&
1'
b011 2
13
14
#46950
04
#47000
0'
b111 2
03
14
#47050
04
#47100
14
#47150
04
0=
#47200
b110 2
14
#47250
04
#47300
0&
1(
b100 2
14
#47350
04
#47400
0(
b000 2
14
#47450
04
#47500
14
#47550
04
1=
#47600
b001 2
14
#47650
04
#47700
1&
1'
b011 2
13
14
#47750
04
#47800
0'
b111 2
03
14
#47850
04
#47900
14
#47950
04
0=
#48000
b110 2
14
#48050
04
#48100
0&
1(
b100 2
14
#48150
04
#48200
0(
b000 2
14
#48250
04
#48300
14
#48350
04
1=
#48400
b001 2
14
#48450
04
#48500
1&
1'
b011 2
13
14
#48550
04
#48600
0'
b111 2
03
14
#48650
04
#48700
14
#48750
04
0=
#48800
b110 2
14
#48850
04
#48900
0&
1(
b100 2
14
#48950
04
#49000
0(
b000 2
14
#49050
04
#49100
14
#49150
04
1=
#49200
b001 2
14
#49250
04
#49300
1&
1'
b011 2
13
14
#49350
04
#49400
0'
b111 2
03
14
#49450
04
#49500
14
#49550
04
0=
#49600
b110 2
14
#49650
04
#49700
0&
1(
b100 2
14
#49750
04
#49800
0(
b000 2
14
#49850
04
#49900
14
#49950
04
1=
#50000
b001 2
14
#50050
04
#50100
1&
1'
b011 2
13
14
#50150
04
#50200
0'
b111 2
03
14
#50250
04
#50300
14
#50350
04
0=
#50400
b110 2
14
#50450
04
#50500
0&
1(
b100 2
14
#50550
04
#50600
0(
b000 2
14
#50650
04
#50700
14
#50750
04
1=
#50800
b001 2
14
#50850
04
#50900
1&
1'
b011 2
13
14
#50950
04
#51000
0'
b111 2
03
14
#51050
04
#51100
14
#51150
04
0=
#51200
b110 2
14
#51250
04
#51300
0&
1(
b100 2
14
#51350
04
#51400
0(
b000 2
14
#51450
04
#51500
14
#51550
04
1=
#51600
b001 2
14
#51650
04
#51700
1&
1'
b011 2
13
14
#51750
04
#51800
0'
b111 2
03
14
#51850
04
#51900
14
#51950
04
1;
0=
#52000
b110 2
14
#52050
04
#52100
0&
1(
b100 2
14
#52150
04
#52200
0(
b000 2
14
#52250
04
#52300
14
#52350
04
1=
#52400
b001 2
14
#52450
04
#52500
1&
1'
b011 2
13
14
#52550
04
#52600
0'
b00000000000000000000000000000000000000000000000000000000000000000000000000000000000000000000000000000000000000000000000000000001 )
b111 2
03
14
b00000000000000000000000000000000000000000000000000000000000000000000000000000000000000000000000000000000000000000000000000000001 @
#52650
04
#52700
14
#52750
04
0=
#52800
b110 2
14
#52850
04
#52900
0&
1(
b100 2
14
#52950
04
#53000
0(
b000 2
14
#53050
04
#53100
14
#53150
04
1=
#53200
b001 2
14
#53250
04
#53300
1&
1'
b011 2
13
14
#53350
04
